mcp_prac/__init__.py
mcp_prac/__main__.py
mcp_prac/weather.py
mcp_prac-0.1.8.dist-info/METADATA
mcp_prac-0.1.8.dist-info/WHEEL
mcp_prac-0.1.8.dist-info/entry_points.txt
mcp_prac-0.1.8.dist-info/top_level.txt
mcp_prac-0.1.8.dist-info/RECORD
