Metadata-Version: 2.4
Name: mcp_prac
Version: 0.1.8
Summary: Add your description here
Requires-Python: >=3.13
Requires-Dist: httpx>=0.28.1
Requires-Dist: mcp>=1.20.0
Requires-Dist: openai>=2.7.1
Requires-Dist: python-dotenv>=1.2.1
